irekua_models/__init__.py
irekua_models/apps.py
irekua_models/settings.py
irekua_models/version.py
irekua_models/migrations/0001_initial.py
irekua_models/migrations/__init__.py
irekua_models/models/__init__.py
irekua_models/models/model.py
irekua_models/models/model_prediction.py
irekua_models/models/model_version.py
project/__init__.py
project/settings.py
project/urls.py
project/wsgi.py
irekua_models-0.1.3.dist-info/LICENCE
irekua_models-0.1.3.dist-info/METADATA
irekua_models-0.1.3.dist-info/WHEEL
irekua_models-0.1.3.dist-info/top_level.txt
irekua_models-0.1.3.dist-info/RECORD
