Metadata-Version: 2.1
Name: irekua-models
Version: 0.1.3
Summary: Irekua AI model registry
Home-page: https://github.com/CONABIO-audio/irekua-models
Author: CONABIO, Gustavo Everardo Robredo Esquivelzeta, Santiago Martínez Balvanera
Author-email: erobredo@conabio.gob.mx, smartinez@conabio.gob.mx
License: BSD License
Platform: UNKNOWN
Classifier: Environment :: Web Environment
Classifier: Framework :: Django
Classifier: Framework :: Django :: 3.0
Classifier: Intended Audience :: Developers
Classifier: License :: OSI Approved :: BSD License
Classifier: Operating System :: OS Independent
Classifier: Programming Language :: Python
Classifier: Programming Language :: Python :: 3.5
Classifier: Programming Language :: Python :: 3.6
Classifier: Programming Language :: Python :: 3.7
Classifier: Topic :: Internet :: WWW/HTTP
Classifier: Topic :: Internet :: WWW/HTTP :: Dynamic Content
Requires-Dist: irekua-database
